interview_generator/__init__.py
interview_generator/analyzers/__init__.py
interview_generator/analyzers/complexity_analyzer.py
interview_generator/analyzers/context_extractor.py
interview_generator/analyzers/pattern_detector.py
interview_generator/cli/__init__.py
interview_generator/cli/main.py
interview_generator/cli/commands/__init__.py
interview_generator/cli/commands/analyze.py
interview_generator/cli/commands/config.py
interview_generator/cli/commands/validate.py
interview_generator/cli/utils/__init__.py
interview_generator/cli/utils/formatters.py
interview_generator/cli/utils/progress.py
interview_generator/cli/utils/validators.py
interview_generator/core/__init__.py
interview_generator/core/application.py
interview_generator/core/pipeline.py
interview_generator/generators/__init__.py
interview_generator/generators/question_categorizer.py
interview_generator/generators/question_generator.py
interview_generator/generators/question_validator.py
interview_generator/llm/__init__.py
interview_generator/llm/llm_integration.py
interview_generator/llm/prompt_templates.py
interview_generator/models/__init__.py
interview_generator/models/analysis_models.py
interview_generator/models/config_models.py
interview_generator/models/context_models.py
interview_generator/models/question_models.py
interview_generator/output/__init__.py
interview_generator/output/file_exporter.py
interview_generator/output/output_formatter.py
interview_generator/output/progress_tracker.py
interview_generator/output/report_generator.py
interview_generator/output/formatters/__init__.py
interview_generator/output/formatters/json_formatter.py
interview_generator/output/formatters/markdown_formatter.py
interview_generator/parsers/__init__.py
interview_generator/parsers/code_parser.py
interview_generator/utils/__init__.py
interview_generator/utils/config_manager.py
interview_generator/utils/file_discovery.py
interview_generator-1.0.0.dist-info/licenses/LICENSE
interview_generator-1.0.0.dist-info/METADATA
interview_generator-1.0.0.dist-info/WHEEL
interview_generator-1.0.0.dist-info/entry_points.txt
interview_generator-1.0.0.dist-info/top_level.txt
interview_generator-1.0.0.dist-info/RECORD
